{
  "3453900": {
    "proofs": {
      "risc0": "\"\""
    }
  },
  "3454000": {
    "proofs": {
      "risc0": "\"\""
    }
  },
  "3454200": {
    "proofs": {
      "risc0": "\"\""
    }
  },
  "3454300": {
    "proofs": {
      "risc0": "\"\""
    }
  },
  "3454400": {
    "proofs": {
      "risc0": "\"\""
    }
  },
  "3454600": {
    "proofs": {
      "risc0": "\"\""
    }
  },
  "3454700": {
    "proofs": {
      "risc0": "\"\""
    }
  },
  "3454900": {
    "proofs": {
      "risc0": "\"\""
    }
  },
  "3455000": {
    "proofs": {
      "risc0": "\"\""
    }
  },
  "3455100": {
    "proofs": {
      "risc0": "\"\""
    }
  },
  "3455300": {
    "proofs": {
      "risc0": "\"\""
    }
  },
  "3455500": {
    "proofs": {
      "risc0": "\"\""
    }
  },
  "3455600": {
    "proofs": {
      "risc0": "\"\""
    }
  },
  "3455700": {
    "proofs": {
      "risc0": "\"\""
    }
  },
  "3455800": {
    "proofs": {
      "risc0": "\"\""
    }
  },
  "3456000": {
    "proofs": {
      "risc0": "\"\""
    }
  },
  "3456100": {
    "proofs": {
      "risc0": "\"\""
    }
  },
  "3456300": {
    "proofs": {
      "risc0": "\"\""
    }
  },
  "3456500": {
    "proofs": {
      "risc0": "\"\""
    }
  },
  "3456700": {
    "proofs": {
      "risc0": "\"\""
    }
  },
  "3456800": {
    "proofs": {
      "risc0": "\"\""
    }
  },
  "3456900": {
    "proofs": {
      "risc0": "\"\""
    }
  },
  "3457100": {
    "proofs": {
      "risc0": "\"\""
    }
  },
  "3457200": {
    "proofs": {
      "risc0": "\"\""
    }
  },
  "3457400": {
    "proofs": {
      "risc0": "\"\""
    }
  },
  "3457500": {
    "proofs": {
      "risc0": "\"\""
    }
  },
  "3457700": {
    "proofs": {
      "risc0": "\"\""
    }
  },
  "3457800": {
    "proofs": {
      "risc0": "\"\""
    }
  },
  "3458000": {
    "proofs": {
      "risc0": "\"\""
    }
  },
  "3458100": {
    "proofs": {
      "risc0": "\"\""
    }
  },
  "3458300": {
    "proofs": {
      "risc0": "\"\""
    }
  },
  "3458400": {
    "proofs": {
      "risc0": "\"\""
    }
  },
  "3458500": {
    "proofs": {
      "risc0": "\"\""
    }
  },
  "3458700": {
    "proofs": {
      "risc0": "\"\""
    }
  },
  "3458900": {
    "proofs": {
      "risc0": "\"\""
    }
  },
  "3459000": {
    "proofs": {
      "risc0": "\"\""
    }
  }
}
