{
  "3510000": {
    "proofs": {
      "risc0": "\"\""
    }
  },
  "3510200": {
    "proofs": {
      "risc0": "\"\""
    }
  },
  "3510300": {
    "proofs": {
      "risc0": "\"\""
    }
  },
  "3510600": {
    "proofs": {
      "risc0": "\"\""
    }
  },
  "3510700": {
    "proofs": {
      "risc0": "\"\""
    }
  },
  "3510800": {
    "proofs": {
      "risc0": "\"\""
    }
  },
  "3511000": {
    "proofs": {
      "risc0": "\"\""
    }
  },
  "3511100": {
    "proofs": {
      "risc0": "\"\""
    }
  },
  "3511300": {
    "proofs": {
      "risc0": "\"\""
    }
  },
  "3511400": {
    "proofs": {
      "risc0": "\"\""
    }
  },
  "3511500": {
    "proofs": {
      "risc0": "\"\""
    }
  },
  "3511700": {
    "proofs": {
      "risc0": "\"\""
    }
  }
}
